proteometer/__init__.py
proteometer/abundance.py
proteometer/alignment.py
proteometer/barcode.py
proteometer/fasta.py
proteometer/lip.py
proteometer/lip_analysis.py
proteometer/normalization.py
proteometer/params.py
proteometer/parse_metadata.py
proteometer/peptide.py
proteometer/ptm.py
proteometer/ptm_analysis.py
proteometer/py.typed
proteometer/quality_control_plots.py
proteometer/residue.py
proteometer/rollup.py
proteometer/stats.py
proteometer/utils.py
proteometer-0.4.0.dist-info/licenses/AUTHORS.md
proteometer-0.4.0.dist-info/licenses/LICENSE
proteometer-0.4.0.dist-info/METADATA
proteometer-0.4.0.dist-info/WHEEL
proteometer-0.4.0.dist-info/top_level.txt
proteometer-0.4.0.dist-info/RECORD
