Metadata-Version: 2.4
Name: proteometer
Version: 0.4.0
Summary: Add a short description here
Author-email: Song Feng <song.feng@pnnl.gov>, Jordan Rozum <jordan.rozum@pnnl.gov>
Requires-Python: >=3.12
License-File: LICENSE
License-File: AUTHORS.md
Requires-Dist: numpy<3,>=2.2.1
Requires-Dist: pandas<3,>=2.2.3
Requires-Dist: scipy<2,>=1.14.1
Requires-Dist: statsmodels<0.15,>=0.14.4
Requires-Dist: biopython<2,>=1.84
Requires-Dist: matplotlib<4,>=3.10.1
Requires-Dist: pingouin<0.6,>=0.5.5
Requires-Dist: seaborn<0.14,>=0.13.2
Dynamic: license-file
